skill_alerts/LICENSE.md
skill_alerts/README.md
skill_alerts/__init__.py
skill_alerts/skill.json
skill_alerts/version.py
skill_alerts/locale/en-us/dialog/confirm_alert_playback.dialog
skill_alerts/locale/en-us/dialog/confirm_alert_recurring.dialog
skill_alerts/locale/en-us/dialog/confirm_alert_recurring_playback.dialog
skill_alerts/locale/en-us/dialog/confirm_alert_recurring_script.dialog
skill_alerts/locale/en-us/dialog/confirm_alert_script.dialog
skill_alerts/locale/en-us/dialog/confirm_alert_set.dialog
skill_alerts/locale/en-us/dialog/confirm_cancel_alert.dialog
skill_alerts/locale/en-us/dialog/confirm_cancel_all.dialog
skill_alerts/locale/en-us/dialog/confirm_dismiss_alert.dialog
skill_alerts/locale/en-us/dialog/confirm_snooze_alert.dialog
skill_alerts/locale/en-us/dialog/confirm_timer_started.dialog
skill_alerts/locale/en-us/dialog/error_audio_reminder_too_far.dialog
skill_alerts/locale/en-us/dialog/error_no_duration.dialog
skill_alerts/locale/en-us/dialog/error_no_scheduled_kind_to_cancel.dialog
skill_alerts/locale/en-us/dialog/error_no_time.dialog
skill_alerts/locale/en-us/dialog/error_nothing_to_cancel.dialog
skill_alerts/locale/en-us/dialog/expired_alert.dialog
skill_alerts/locale/en-us/dialog/expired_audio_alert_intro.dialog
skill_alerts/locale/en-us/dialog/expired_reminder.dialog
skill_alerts/locale/en-us/dialog/list_alert.dialog
skill_alerts/locale/en-us/dialog/list_alert_intro.dialog
skill_alerts/locale/en-us/dialog/list_alert_missed_intro.dialog
skill_alerts/locale/en-us/dialog/list_alert_none_missed.dialog
skill_alerts/locale/en-us/dialog/list_alert_none_upcoming.dialog
skill_alerts/locale/en-us/dialog/list_alert_repeating.dialog
skill_alerts/locale/en-us/dialog/next_alert_named.dialog
skill_alerts/locale/en-us/dialog/next_alert_unnamed.dialog
skill_alerts/locale/en-us/dialog/quiet_hours_end.dialog
skill_alerts/locale/en-us/dialog/quiet_hours_start.dialog
skill_alerts/locale/en-us/dialog/timer_status.dialog
skill_alerts/neon_skill_alerts.egg-info/PKG-INFO
skill_alerts/neon_skill_alerts.egg-info/SOURCES.txt
skill_alerts/neon_skill_alerts.egg-info/dependency_links.txt
skill_alerts/neon_skill_alerts.egg-info/entry_points.txt
skill_alerts/neon_skill_alerts.egg-info/requires.txt
skill_alerts/neon_skill_alerts.egg-info/top_level.txt
neon_skill_alerts-3.0.1.dist-info/LICENSE.md
neon_skill_alerts-3.0.1.dist-info/METADATA
neon_skill_alerts-3.0.1.dist-info/WHEEL
neon_skill_alerts-3.0.1.dist-info/entry_points.txt
neon_skill_alerts-3.0.1.dist-info/top_level.txt
neon_skill_alerts-3.0.1.dist-info/RECORD
