Metadata-Version: 2.1
Name: neon-skill-alerts
Version: 3.0.1
Home-page: https://github.com/NeonGeckoCom/skill-alerts
Author: Neongecko
Author-email: developers@neon.ai
License: BSD-3-Clause
License-File: LICENSE.md
Requires-Dist: json-database~=0.5
Requires-Dist: neon-utils~=1.12
Requires-Dist: combo-lock~=0.2
Requires-Dist: ovos-utils>=0.0.32,~=0.0
Requires-Dist: ovos-bus-client>=0.0.3,~=0.0
Requires-Dist: ovos-workshop>=0.0.12,~=0.0
Provides-Extra: test
Requires-Dist: neon-minerva[padatious]~=0.3; extra == "test"
